{
	"format_version": "1.8.0",
	"animations": {
		"bash": {
			"animation_length": 1.25,
			"bones": {
				"head": {
					"rotation": {
						"0.0": {
							"vector": [0, 0, 0]
						},
						"0.25": {
							"vector": [-5.5, 0, 0]
						},
						"0.75": {
							"vector": [0, 0, 0]
						}
					}
				},
				"torso": {
					"rotation": {
						"0.0": {
							"vector": [0, 0, 0]
						},
						"0.25": {
							"vector": [2.5, 0, 0]
						},
						"0.75": {
							"vector": [0, 0, 0]
						}
					}
				},
				"rightArm": {
					"rotation": {
						"0.0": {
							"vector": [-52.38443, -40.84182, -26.744]
						},
						"0.3333": {
							"vector": [-102.85345, 29.66655, -32.75014]
						},
						"0.75": {
							"vector": [-52.38443, -40.84182, -26.744]
						}
					}
				},
				"leftArm": {
					"rotation": {
						"0.0": {
							"vector": [0, 0, 0]
						},
						"0.25": {
							"vector": [1.6919, 1.21729, -9.71784]
						},
						"0.75": {
							"vector": [0, 0, 0]
						}
					}
				},
				"rightLeg": {
					"rotation": {
						"0.0": {
							"vector": [0, 0, 0]
						},
						"0.25": {
							"vector": [7.5772, -5.85119, 1.81068]
						},
						"0.75": {
							"vector": [0, 0, 0]
						}
					}
				},
				"leftLeg": {
					"rotation": {
						"0.0": {
							"vector": [0, 0, 0]
						},
						"0.25": {
							"vector": [17.5, 0, -2.5]
						},
						"0.75": {
							"vector": [0, 0, 0]
						}
					}
				}
			}
		}
	},
	"geckolib_format_version": 2
}